LICENSE
MANIFEST.in
README.rst
klaus.1
pyproject.toml
setup.py
klaus/__init__.py
klaus/cli.py
klaus/ctagscache.py
klaus/ctagsutils.py
klaus/diff.py
klaus/highlighting.py
klaus/markup.py
klaus/repo.py
klaus/utils.py
klaus/views.py
klaus.egg-info/PKG-INFO
klaus.egg-info/SOURCES.txt
klaus.egg-info/dependency_links.txt
klaus.egg-info/entry_points.txt
klaus.egg-info/not-zip-safe
klaus.egg-info/requires.txt
klaus.egg-info/top_level.txt
klaus/contrib/__init__.py
klaus/contrib/app_args.py
klaus/contrib/wsgi.py
klaus/contrib/wsgi_autoreload.py
klaus/contrib/wsgi_autoreloading.py
klaus/static/favicon.png
klaus/static/klaus.css
klaus/static/klaus.js
klaus/static/pygments.css
klaus/static/robots.txt
klaus/templates/base.html
klaus/templates/blame_blob.html
klaus/templates/history.html
klaus/templates/history.inc.html
klaus/templates/index.html
klaus/templates/repo_list.html
klaus/templates/skeleton.html
klaus/templates/submodule.html
klaus/templates/tree.inc.html
klaus/templates/view_blob.html
klaus/templates/view_commit.html
tests/test_blame.py
tests/test_contrib.py
tests/test_make_app.py
tests/test_manpage.py
tests/test_utils.py
tests/test_views.py