Metadata-Version: 2.1
Name: klaus
Version: 3.0.1
Summary: The first Git web viewer that Just Works™.
Home-page: https://github.com/jonashaag/klaus
Author: Jonas Haag
Author-email: jonas@lophus.org
Classifier: Development Status :: 5 - Production/Stable
Classifier: Topic :: Internet :: WWW/HTTP :: Dynamic Content
Classifier: Topic :: Internet :: WWW/HTTP :: WSGI :: Application
Classifier: Topic :: Software Development :: Version Control
Classifier: Environment :: Web Environment
Classifier: Intended Audience :: Developers
Classifier: License :: OSI Approved :: ISC License (ISCL)
Classifier: Programming Language :: Python
Classifier: Programming Language :: Python :: 2.7
Classifier: Programming Language :: Python :: 3
Requires-Python: >=3.7
License-File: LICENSE
Requires-Dist: flask
Requires-Dist: Werkzeug>=0.15.0
Requires-Dist: pygments
Requires-Dist: httpauth>=0.4
Requires-Dist: humanize
Requires-Dist: dulwich>=0.19.3
